{
  "start": {
    "text": "You wake up. Your beans are gone. The jar is empty. A single bean shell lies on the floor.",
    "choices": [
      { "label": "Investigate the neighbor", "next": "neighborDoor" },
      { "label": "Follow the bean trail outside", "next": "forestPath" },
      { "label": "Call the Bureau of Legumes & Lost Goods", "next": "bureauIntro" }
    ]
  },

  "neighborDoor": {
    "text": "You knock on your neighbor’s door. They open it just a crack. Their eyes dart around nervously.",
    "choices": [
      { "label": "Accuse them immediately", "next": "accuseNeighbor" },
      { "label": "Offer them a granola bar as a bribe", "next": "bribeNeighbor" },
      { "label": "Sneak into their backyard", "next": "backyardSneak" },
      { "label": "Ask about their attic", "next": "neighborWeirdAttic" }

    ]
  },

  "accuseNeighbor": {
  "text": "You point dramatically. 'YOU stole my beans!' Your neighbor gasps. 'I would NEVER! But... I did see someone lurking around your house last night.'",
  "choices": [
    { "label": "Ask who they saw", "next": "neighborSaw" },
    { "label": "Storm off dramatically", "next": "stormOff" },
    { "label": "Throw a piece of bread at them (why not?)", "next": "breadFight" }
  ]
},


  "neighborSaw": {
    "text": "'It was... a raccoon. But not a normal one. This one wore a tiny bandana.'",
    "choices": [
      { "label": "Head to the forest", "next": "forestPath" },
      { "label": "Ask more about the raccoon", "next": "raccoonLore" }
    ]
  },

  "raccoonLore": {
    "text": "Your neighbor whispers, 'They call him... The Bean Bandit. Leader of the Raccoon Syndicate.'",
    "choices": [
      { "label": "Go confront the syndicate", "next": "raccoonEncounter" },
      { "label": "Pretend you’re not terrified", "next": "pretendBrave" }
    ]
  },

  "pretendBrave": {
    "text": "You puff out your chest. 'I fear no raccoon.' Your neighbor nods politely, clearly unconvinced.",
    "choices": [
      { "label": "Go to the forest anyway", "next": "forestPath" },
      { "label": "Go home and rethink your life", "next": "endingCoward" }
    ]
  },

  "stormOff": {
    "text": "You storm off, but trip over a garden gnome. The neighbor watches silently.",
    "choices": [
      { "label": "Recover your dignity and continue", "next": "start" },
      { "label": "Lie on the ground and give up", "next": "endingGiveUp" }
    ]
  },

  "breadFight": {
  "text": "Your neighbor stares at you. 'What was that for? You wanna fight me?'",
  "choices": [
    { "label": "Throw another piece of bread at your neighbor", "next": "powPow" },
    { "label": "Apologize and give him a granola bar", "next": "bribeNeighbor" }
  ]
},

  "bribeNeighbor": {
    "text": "You offer a granola bar. Your neighbor snatches it instantly. 'Okay fine, I DID see something. A trail of beans leading into the woods.'",
    "choices": [
      { "label": "Follow the trail", "next": "forestPath" },
      { "label": "Ask why they’re so obsessed with granola bars", "next": "granolaLore" }
    ]
  },

  "granolaLore": {
    "text": "'I haven't eaten real food in days,' they whisper. 'The raccoons... they took everything.'",
    "choices": [
      { "label": "Team up with the neighbor", "next": "teamUp" },
      { "label": "Go alone", "next": "forestPath" }
    ]
  },

  "teamUp": {
    "text": "Your neighbor grabs a broom. 'Let’s get your beans back.'",
    "choices": [
      { "label": "Charge into the forest together", "next": "raccoonEncounterTeam" }
    ]
  },

  "backyardSneak": {
    "text": "You sneak into their backyard. You find... a half‑eaten can of beans. Suspicious.",
    "choices": [
      { "label": "Confront them with the evidence", "next": "confrontBackyard" },
      { "label": "Taste the beans (why?)", "next": "tasteBeans" }
    ]
  },

  "confrontBackyard": {
    "text": "Your neighbor panics. 'Okay fine! I stole ONE bean. But the rest? The raccoons took them!'",
    "choices": [
      { "label": "Accept their apology", "next": "start" },
      { "label": "Demand compensation", "next": "endingCompensation" }
    ]
  },

  "tasteBeans": {
    "text": "You taste the beans. They are... raccoon‑flavored. You immediately regret everything.",
    "choices": [
      { "label": "Go to the forest", "next": "forestPath" },
      { "label": "Sit down and cry", "next": "endingCry" }
    ]
  },

  "forestPath": {
  "text": "You follow the bean shells into the woods. Strange chittering echoes around you.",
  "choices": [
    { "label": "Investigate the sound", "next": "raccoonEncounter" },
    { "label": "Turn back", "next": "start" },
    { "label": "Follow a strange glowing crack in the air", "next": "breakReality" },
    { "label": "Talk to the mysterious old man playing chess", "next": "chessChallenge" },
    { "label": "Look at that weird stool thingy which looks mysterious", "next": "inventoryTest"},
    { "label": "Inspect the weird stool more closely", "next": "forestStoolInspect" }, { "label": "Jump into a mysterious hole", "next": "forestDeepHole" }
  ]
},


  "raccoonEncounter": {
  "text": "A raccoon wearing a tiny bandana steps out. 'So... you’ve come for your beans.'",
  "choices": [
    { "label": "Negotiate", "next": "negotiateRaccoon" },
    { "label": "Fight", "next": "fightRaccoon" },
    { "label": "Join the syndicate", "next": "joinSyndicate" },
    { "label": "Ask the raccoon to wait for a minute and study ancient bean magic", "next": "beanMagic" },
    { "label": "Pause and meditate with the raccoon", "next": "raccoonMeditation" }

  ]
},

  "raccoonEncounterTeam": {
    "text": "You and your neighbor burst into the clearing. The raccoon bandit sighs. 'Two of you? Really?'",
    "choices": [
      { "label": "Let your neighbor handle it", "next": "neighborFight" },
      { "label": "Handle it yourself", "next": "raccoonEncounter" }
    ]
  },

  "neighborFight": {
    "text": "Your neighbor charges with the broom. The raccoon sidesteps effortlessly. 'Pathetic,' it mutters.",
    "choices": [
      { "label": "Help your neighbor", "next": "fightRaccoon" },
      { "label": "Run away", "next": "endingCoward" }
    ]
  },

  "negotiateRaccoon": {
    "text": "You sit down. The raccoon sits too. 'Your beans were delicious,' it admits. 'But perhaps we can strike a deal.'",
    "choices": [
      { "label": "Offer a trade", "next": "tradeOffer" },
      { "label": "Demand your beans back", "next": "demandBeans" }
    ]
  },

  "tradeOffer": {
    "text": "'Bring me three granola bars,' the raccoon says. 'Then we talk.'",
    "choices": [
      { "label": "Agree to the deal", "next": "endingQuest" },
      { "label": "Refuse", "next": "fightRaccoon" }
    ]
  },

  "demandBeans": {
    "text": "You demand your beans back. The raccoon laughs. 'Bold. I respect that.' It returns half the beans.",
    "choices": [
      { "label": "Accept the partial victory", "next": "endingHalfBeans" },
      { "label": "Fight for the rest", "next": "fightRaccoon" }
    ]
  },

  "fightRaccoon": {
    "text": "You charge. The raccoon charges. It’s dramatic. It’s chaotic. It’s... surprisingly adorable.",
    "choices": [
      { "label": "Keep fighting", "next": "fightOutcome" },
      { "label": "Retreat", "next": "endingCoward" },
      { "label": "Hesitate to realize that you are fighting a raccoon over beans instead of getting a job, getting married, or doing something better in life, until the raccoon punches you.", "next": "fightLose" }
    ]
  },

  "fightLose": {
    "text": "The raccoon chitters triumphantly as you collapse onto the grass. Before you can get back up, he grabs your precious beans, stuffs them into a tiny backpack, and scurries off into the shadows.",
    "choices": [
      { "label": "Follow the pawprints", "next": "followPawprints" },
      { "label": "Search the neighborhood", "next": "searchNeighborhood" },
      { "label": "Give up and go home", "next": "endingGiveUp" }
    ]
  },

  "followPawprints": {
    "text": "You follow a trail of tiny pawprints leading toward the old park. They stop near a suspicious-looking trash can.",
    "choices": [
      { "label": "Look inside the trash can", "next": "trashCan" },
      { "label": "Search the park", "next": "parkSearch" }
    ]
  },

  "searchNeighborhood": {
    "text": "You scan the neighborhood. A scrap of fabric from the raccoon's tiny backpack is stuck on a fence.",
    "choices": [
      { "label": "Climb the fence", "next": "fenceClimb" },
      { "label": "Look for more clues", "next": "moreClues" }
    ]
  },

  "trashCan": {
    "text": "You peek inside the trash can. Two glowing raccoon eyes stare back. You close the lid immediately.",
    "choices": [
      { "label": "Back away slowly", "next": "endingCoward" },
      { "label": "Open it again (why?)", "next": "endingCry" }
    ]
  },

  "parkSearch": {
    "text": "You search the park and find a tiny raccoon-sized footprint leading into a storm drain.",
    "choices": [
      { "label": "Enter the storm drain", "next": "endingSyndicate" },
      { "label": "Turn back", "next": "start" }
    ]
  },

  "fenceClimb": {
    "text": "You climb the fence and land in someone's backyard. A raccoon stares at you from a tree branch, holding your beans mockingly.",
    "choices": [
      { "label": "Chase it", "next": "moreClues" },
      { "label": "Retreat", "next": "endingCoward" }
    ]
  },

  "moreClues": {
    "text": "You find a tiny map drawn in crayon. It seems to show a raccoon hideout beneath the old playground.",
    "choices": [
      { "label": "Investigate the playground", "next": "parkSearch" },
      { "label": "Ignore the map", "next": "endingGiveUp" }
    ]
  },
"fightOutcome": {
  "text": "After a flurry of fur and fists, you stand victorious. The raccoon bows. 'You have earned your beans.'",
  "choices": [
    { "label": "Take your beans and go home", "next": "forgetPath" }
  ]
},

"forgetPath": {
  "text": "You have forgotten your way home.",
  "choices": [
    { "label": "Go left", "next": "dropBeans" },
    { "label": "Go straight", "next": "dropBeans" },
    { "label": "Go right", "next": "dropBeans" }
  ]
},

"dropBeans": {
  "text": "You trip over a piece of bread on the ground, and drop the jar of beans. You watch your beloved beans scatter across the dirt.",
  "choices": [
    { "label": "Sit down and cry", "next": "endingCry" },
    { "label": "Taste the beans", "next": "fakeBeans" }
  ]
},

"fakeBeans": {
  "text": "You taste the beans. They taste like wax. These aren't your beans at all.",
  "choices": [
    { "label": "Confront the raccoon", "next": "raccoonEncounter" }
  ]
},

      
  "joinSyndicate": {
    "text": "You kneel. 'Teach me your ways.' The raccoon nods. 'Welcome, Beanling.'",
    "choices": [
      { "label": "Accept your new life", "next": "endingSyndicate" }
    ]
  },

  "bureauIntro": {
  "text": "You arrive at the Bureau of Legumes & Lost Goods. A tired detective looks up. 'Another bean theft?'",
  "choices": [
    { "label": "File a report", "next": "fileReport" },
    { "label": "Ask to see the bean database", "next": "beanDatabase" },
    { "label": "Ask about classified bean anomalies", "next": "metaAwareness" },
    { "label": "Ask about the basement", "next": "bureauBasement" },
    { "label": "Look behind the filing cabinets", "next": "bureauSecretHallway" }
  ]
},


  "fileReport": {
    "text": "You fill out 47 pages of paperwork. The detective stamps it. 'We’ll get back to you in 6–8 months.'",
    "choices": [
      { "label": "Cry", "next": "endingCry" },
      { "label": "Go solve it yourself", "next": "start" },
      { "label": "Wait the 6-8 months", "next": "waitLong"}
    ]
  },
  "waitLong": {
    "text": "ENDING: After 50 years without your beans, you get a phone call. The detective tells you that he will find your beans. Before you can respond, your fake teeth fall out of your mouth by accident, and you end up telling him absolute gibberish. The detective is offended, and hangs up.",
    "choices": []
  },
  "beanDatabase": {
    "text": "The detective sighs. 'Fine.' He opens a massive file labeled BEAN CRIMES.",
    "choices": [
      { "label": "Search for raccoon activity", "next": "bureauRaccoon" },
      { "label": "Search for neighbor activity", "next": "bureauNeighbor" }
    ]
   },

  "bureauRaccoon": {
    "text": "The file is huge. The raccoon syndicate has been active for years.",
    "choices": [
      { "label": "Go to the forest", "next": "forestPath" }
    ]
  },

  "bureauNeighbor": {
    "text": "Your neighbor has 14 prior bean‑related incidents. Interesting.",
    "choices": [
      { "label": "Confront them", "next": "neighborDoor" }
    ]
  },

  "endingVictory": {
    "text": "ENDING: You defeated the raccoon and reclaimed your beans. You are now a legend.",
    "choices": []
  },

  "endingHalfBeans": {
    "text": "ENDING: You got half your beans back. Not perfect, but acceptable.",
    "choices": []
  },

  "endingSyndicate": {
    "text": "ENDING: You join the raccoon syndicate. You rise through the ranks. You become the Bean King.",
    "choices": []
  },

  "endingCoward": {
    "text": "ENDING: You ran away. The beans remain lost. The shame is eternal.",
    "choices": []
  },

  "endingCry": {
    "text": "ENDING: You sit down and cry. The forest watches silently.",
    "choices": []
  },

  "endingGiveUp": {
    "text": "ENDING: You give up entirely. The beans are gone forever.",
    "choices": []
  },
  "endingCompensation": {
    "text": "ENDING: Your neighbor gives you $3 as compensation. You buy new beans. Life goes on.",
    "choices": []
  },

  "endingQuest": {
    "text": "ENDING: You embark on a new quest to gather granola bars. The saga continues.",
    "choices": []
  },

    "powPow": {
    "text": "ENDING: Your neighbor knows karate, and punches you in the face. You run away, and trip over a lawn gnome. You forget about your beans, and decide to never throw pieces of bread at your neighbor again.",
    "choices": []
  },

  "chessChallenge": {
    "text": "A mysterious old man steps out of the bushes. 'Solve your bean problem? Beat me in chess.'",
    "choices": [
      { "label": "Accept the challenge", "next": "chessPlay" },
      { "label": "Flip the chessboard and run", "next": "endingCoward" },
      { "label": "Ask if raccoons play chess", "next": "chessLore" },
      { "label": "Ask him if he knows how to meditate because old people do that a lot", "next": "oldManMeditate" }
    ]
  },
  "oldManMeditate": {
    "text": "'Er, yes, I do meditate. Would you like to learn?' The old man asks calmly.",
    "choices": [
      { "label":"Learn to meditate", "next": "forestMeditation" },
      { "label":"Politely decline and go back to the chess challenge", "next": "chessChallenge" }
    ]
  },
  "chessPlay": {
    "text": "You sit at a stone table. The old man moves a pawn. Your beans depend on this.",
    "choices": [
      { "label": "Open with the Sicilian Defense", "next": "endingChessMaster" },
      { "label": "Blunder your queen immediately", "next": "endingChessFail" },
      { "label": "Eat a pawn (literally)", "next": "endingPawnEater" }
    ]
  },

  "chessLore": {
    "text": "'Raccoons? No. They prefer checkers,' the old man says. 'Weak creatures.'",
    "choices": [
      { "label": "Play chess anyway", "next": "chessPlay" },
      { "label": "Go find raccoons who play checkers", "next": "raccoonEncounter" }
    ]
  },

  "endingChessMaster": {
    "text": "ENDING: You win flawlessly. The old man bows. 'You are the Bean Grandmaster now.'",
    "choices": []
  },

  "endingChessFail": {
    "text": "ENDING: You lose in four moves. The old man laughs for 17 minutes straight.",
    "choices": []
  },

  "endingPawnEater": {
    "text": "ENDING: You eat a pawn. It tastes like regret. The old man faints.",
    "choices": []
  },

  "breakReality": {
    "text": "You poke the air. A crack forms in reality. Light leaks out.",
    "choices": [
      { "label": "Step through the crack", "next": "voidEntrance" },
      { "label": "Close the crack politely", "next": "start" },
      { "label": "Widen the crack", "next": "realityShatter" },
      { "label": "Peer deeper into the crack", "next": "breakRealityDeep" }

    ]
  },

  "voidEntrance": {
    "text": "You enter the Void. A giant cosmic bean floats before you.",
    "choices": [
      { "label": "Speak to the bean", "next": "cosmicBeanTalk" },
      { "label": "Eat the cosmic bean", "next": "endingAscension" }
    ]
  },

  "cosmicBeanTalk": {
    "text": "The cosmic bean whispers: 'Your beans were never stolen. They transcended.'",
    "choices": [
      { "label": "Transcend with them", "next": "endingTranscend" },
      { "label": "Reject enlightenment", "next": "start" }
    ]
  },

  "realityShatter": {
    "text": "Reality collapses. You float in a swirling storm of raccoons, beans, and unpaid taxes.",
    "choices": [
      { "label": "Accept your fate", "next": "endingShattered" },
      { "label": "Try to rebuild reality", "next": "rebuildReality" }
    ]
  },

  "rebuildReality": {
    "text": "You rebuild reality, but accidentally make raccoons the dominant species.",
    "choices": [
      { "label": "Bow to your new raccoon overlords", "next": "endingOverlords" },
      { "label": "Reboot reality again", "next": "start" }
    ]
  },

  "endingAscension": {
    "text": "ENDING: You eat the cosmic bean and ascend to a higher plane. You become Bean Itself.",
    "choices": []
  },

  "endingTranscend": {
    "text": "ENDING: You transcend physical form. Your beans transcend with you. Perfect harmony.",
    "choices": []
  },

  "endingShattered": {
    "text": "ENDING: Reality shatters like glass. You drift forever in the Beanstorm.",
    "choices": []
  },

  "endingOverlords": {
    "text": "ENDING: Raccoons rule the universe. You are appointed Royal Bean Advisor.",
    "choices": []
  },

  "metaAwareness": {
    "text": "You suddenly realize you're in a game. The text feels... scripted.",
    "choices": [
      { "label": "Look for the narrator", "next": "findNarrator" },
      { "label": "Try to escape the game", "next": "escapeGame" },
      { "label": "Delete the game from inside the game", "next": "endingDelete" }
    ]
  },

  "findNarrator": {
    "text": "You look up. A giant floating cursor hovers above you.",
    "choices": [
      { "label": "Talk to the cursor", "next": "cursorTalk" },
      { "label": "Throw beans at it", "next": "endingCursorAngry" }
    ]
  },

  "cursorTalk": {
    "text": "The cursor says: 'Stop breaking the fourth wall. I'm busy.'",
    "choices": [
      { "label": "Break the fifth wall instead", "next": "endingFifthWall" },
      { "label": "Return to the story", "next": "start" }
    ]
  },

  "escapeGame": {
    "text": "You run toward the edge of the screen. The world glitches.",
    "choices": [
      { "label": "Jump out of the window", "next": "endingEscape" },
      { "label": "Stay inside the game", "next": "start" }
    ]
  },

  "endingDelete": {
    "text": "ENDING: You delete the game from within the game. Everything stops existing. Including you.",
    "choices": []
  },

  "endingCursorAngry": {
    "text": "ENDING: The cursor becomes angry and drags you into the settings menu forever.",
    "choices": []
  },

  "endingFifthWall": {
    "text": "ENDING: You break the fifth wall. Nobody knows what that means. You win by default.",
    "choices": []
  },

  "endingEscape": {
    "text": "ENDING: You escape the game and appear on someone's desktop. They scream.",
    "choices": []
  },

  "beanMagic": {
    "text": "You discover an ancient spellbook titled 'Legumancy for Beginners'.",
    "choices": [
      { "label": "Cast a bean spell", "next": "castSpell" },
      { "label": "Summon a bean familiar", "next": "beanFamiliar" }
    ]
  },

  "castSpell": {
    "text": "You cast BEANUS MAXIMUS. Something happens.",
    "choices": [
      { "label": "Hope it's good", "next": "endingWizard" },
      { "label": "Panic", "next": "endingExplosion" }
    ]
  },

  "beanFamiliar": {
    "text": "A tiny bean with legs appears. It salutes you.",
    "choices": [
      { "label": "Adopt it", "next": "endingFamiliar" },
      { "label": "Eat it", "next": "endingEatFamiliar" }
    ]
  },

  "endingWizard": {
    "text": "ENDING: You become a Bean Wizard. Your power is immeasurable.",
    "choices": []
  },

  "endingExplosion": {
    "text": "ENDING: The spell explodes. You are now slightly toasted.",
    "choices": []
  },

  "endingFamiliar": {
    "text": "ENDING: You and your bean familiar go on adventures forever.",
    "choices": []
  },

  "endingEatFamiliar": {
    "text": "ENDING: You eat your bean familiar. It was crunchy. You monster.",
    "choices": []
  },
  "inventoryTest": {
    "text": "You find a strange glowing bean shard on a pedestal.",
    "choices": [
      { "label": "Pick up the shard", "next": "inventoryTest", "item": "Bean Shard" },
      { "label": "Proceed deeper into the chamber", "next": "lockedDoor" }
    ]
  },

  "lockedDoor": {
    "text": "A massive stone door blocks your path. A bean-shaped indentation glows faintly.",
    "choices": [
      { "label": "Insert the Bean Shard", "next": "doorOpens", "requires": "Bean Shard" },
      { "label": "Push the door with your bare hands", "next": "endingCoward" }
    ]
  },

  "doorOpens": {
    "text": "The shard fits perfectly. The door rumbles open, revealing a hidden chamber.",
    "choices": [
      { "label": "Enter the chamber", "next": "skillTreeIntro" }
    ]
  },

  "skillTreeIntro": {
    "text": "A glowing mural depicts ancient bean techniques. You feel knowledge flowing into you.",
    "choices": [
      { "label": "Unlock Bean Sense I", "next": "skillUnlocked", "skill": "beanSense" },
      { "label": "Unlock Raccoon Diplomacy I", "next": "skillUnlocked", "skill": "raccoonTalk" },
      { "label": "Ignore the mural", "next": "start" }
    ]
  },

  "skillUnlocked": {
    "text": "You feel a new power awaken within you.",
    "choices": [
      { "label": "Continue", "next": "loreIntro" }
    ]
  },

  "loreIntro": {
    "text": "Ancient carvings line the walls. They depict the history of the Bean War.",
    "choices": [
      { "label": "Record the carvings", "next": "loreSaved", "lore": "Bean War History" },
      { "label": "Move on", "next": "mapIntro" }
    ]
  },

  "loreSaved": {
    "text": "You jot down the carvings into your Beanpedia.",
    "choices": [
      { "label": "Continue", "next": "mapIntro" }
    ]
  },

  "mapIntro": {
    "text": "A stone map appears on the wall, showing several locations.",
    "choices": [
      { "label": "Unlock the Ancient Chamber on your map", "next": "mapSaved", "location": "Ancient Chamber" },
      { "label": "Ignore the map", "next": "chaosIntro" }
    ]
  },

  "mapSaved": {
    "text": "The map glows. You feel the location imprint itself into your mind.",
    "choices": [
      { "label": "Continue", "next": "chaosIntro" }
    ]
  },

  "chaosIntro": {
    "text": "The air crackles. Something chaotic stirs.",
    "choices": [
      { "label": "Trigger Chaos Mode", "next": "chaosEvent", "chaos": true },
      { "label": "Back away slowly", "next": "start" }
    ]
  },

  "chaosEvent": {
    "text": "CHAOS MODE: Reality begins to distort. Raccoons fall from the ceiling. Beans float upward.",
    "choices": [
      { "label": "Embrace the chaos", "next": "endingShattered" },
      { "label": "Try to stabilize reality", "next": "miniGameIntro" }
    ]
  },

  "miniGameIntro": {
    "text": "A glowing puzzle appears before you. Solve it to restore balance.",
    "choices": [
      { "label": "Start the memory mini-game", "next": "miniGameStart", "minigame": "memory" },
      { "label": "Refuse the challenge", "next": "endingCoward" }
    ]
  },

  "miniGameStart": {
    "text": "The mini-game begins...",
    "choices": [
      { "label": "Return to the story", "next": "start" }
    ]
  }
  ,
  "longJourneyStart": {
    "text": "You feel a strange tug in your soul. A whisper: 'Your beans are not lost... only far away.'",
    "choices": [
      { "label": "Follow the whisper", "next": "beanSpirit" },
      { "label": "Ignore it and eat dirt", "next": "endingEatDirt" }
    ]
  },

  "beanSpirit": {
    "text": "A translucent bean spirit appears. 'You seek the True Beans. Few survive the journey.'",
    "choices": [
      { "label": "Accept the quest", "next": "beanTrial1" },
      { "label": "Ask why it's translucent", "next": "beanSpiritLore" }
    ]
  },

  "beanSpiritLore": {
    "text": "'I died in the Great Bean War of 1987,' it says. 'Long story.'",
    "choices": [
      { "label": "Offer condolences", "next": "beanTrial1" },
      { "label": "Ask for the long story", "next": "endingLongStory" }
    ]
  },

  "beanTrial1": {
    "text": "TRIAL 1: You must cross the Bridge of Mild Inconvenience. A sign reads: 'Bridge closed for repairs.'",
    "choices": [
      { "label": "Cross anyway", "next": "beanTrial2" },
      { "label": "Wait patiently", "next": "endingPatience" }
    ]
  },

  "beanTrial2": {
    "text": "TRIAL 2: A raccoon monk blocks your path. 'Solve my riddle: What has beans but is not a bean?'",
    "choices": [
      { "label": "A bean jar", "next": "endingWrongRiddle" },
      { "label": "A human (they have kidneys)", "next": "beanTrial3" },
      { "label": "A raccoon with a tiny backpack", "next": "endingRaccoonOffended" }
    ]
  },

  "beanTrial3": {
    "text": "TRIAL 3: You enter a chamber with three doors: PAST, PRESENT, FUTURE.",
    "choices": [
      { "label": "Enter PAST", "next": "timePast" },
      { "label": "Enter PRESENT", "next": "timePresent" },
      { "label": "Enter FUTURE", "next": "timeFuture" }
    ]
  },

  "timePast": {
    "text": "You arrive at your house yesterday. You see yourself eating beans at 2 AM.",
    "choices": [
      { "label": "Warn past-you", "next": "endingParadox" },
      { "label": "Steal your own beans", "next": "endingSelfTheft" },
      { "label": "Return to the chamber", "next": "beanTrial4" }
    ]
  },

  "timePresent": {
    "text": "You step into the present. Nothing happens. Time is boring.",
    "choices": [
      { "label": "Return", "next": "beanTrial4" }
    ]
  },

  "timeFuture": {
    "text": "You see a future where raccoons rule the world. They salute you.",
    "choices": [
      { "label": "Bow to them", "next": "endingOverlords" },
      { "label": "Return", "next": "beanTrial4" }
    ]
  },

  "beanTrial4": {
    "text": "FINAL TRIAL: A giant stone door reads: 'ONLY THE BEAN-WORTHY MAY ENTER.'",
    "choices": [
      { "label": "Knock politely", "next": "beanGuardian" },
      { "label": "Kick the door", "next": "endingFootPain" }
    ]
  },

  "beanGuardian": {
    "text": "A massive guardian made of beans awakens. 'STATE YOUR PURPOSE.'",
    "choices": [
      { "label": "I want my beans back", "next": "guardianTest" },
      { "label": "I want enlightenment", "next": "endingEnlightenment" }
    ]
  },

  "guardianTest": {
    "text": "'ANSWER THIS: What is the true nature of beans?'",
    "choices": [
      { "label": "Delicious", "next": "endingUnworthy" },
      { "label": "Chaotic neutral", "next": "endingUnworthy" },
      { "label": "A metaphor for the journey we take within ourselves", "next": "beanSanctum" }
    ]
  },

  "beanSanctum": {
    "text": "The guardian bows. The door opens. Inside lies a glowing pedestal.",
    "choices": [
      { "label": "Approach the pedestal", "next": "trueBeansReveal" }
    ]
  },

  "trueBeansReveal": {
    "text": "On the pedestal sits a jar. YOUR jar. Untouched. Perfect. Radiating bean energy.",
    "choices": [
      { "label": "Take the jar", "next": "trueEnding" },
      { "label": "Hesitate dramatically", "next": "endingHesitate" }
    ]
  },

  "trueEnding": {
    "text": "TRUE ENDING: After countless trials, timelines, raccoons, spirits, and cosmic nonsense... you finally reclaim your beans. They are warm. They are perfect. You have won.",
    "choices": []
  },

  "endingEatDirt": {
    "text": "ENDING: You eat dirt. It tastes like dirt. You learn nothing.",
    "choices": []
  },

  "endingLongStory": {
    "text": "ENDING: The bean spirit tells a 9-hour story. You die of boredom.",
    "choices": []
  },

  "endingPatience": {
    "text": "ENDING: You wait 47 years. The bridge never opens.",
    "choices": []
  },

  "endingWrongRiddle": {
    "text": "ENDING: The raccoon monk shakes his head. 'Incorrect.' He bonks you with a stick.",
    "choices": []
  },

  "endingRaccoonOffended": {
    "text": "ENDING: The raccoon monk is offended. He calls his lawyer.",
    "choices": []
  },

  "endingParadox": {
    "text": "ENDING: You warn past-you. Past-you panics. Time collapses.",
    "choices": []
  },

  "endingSelfTheft": {
    "text": "ENDING: You steal your own beans. You create the very problem you tried to solve.",
    "choices": []
  },

  "endingFootPain": {
    "text": "ENDING: You kick the stone door. You break your foot. The door does not care.",
    "choices": []
  },

  "endingEnlightenment": {
    "text": "ENDING: You transcend beans. You become pure legume energy.",
    "choices": []
  },

  "endingUnworthy": {
    "text": "ENDING: The guardian deems you unworthy. You are bean-blasted into the forest.",
    "choices": []
  },

  "endingHesitate": {
    "text": "ENDING: You hesitate for too long. A raccoon steals the jar.",
    "choices": []
  }
    ,
  "longJourneySidePath": {
    "text": "A second whisper calls to you. 'The long journey has many roads. Choose unwisely.'",
    "choices": [
      { "label": "Follow the left whisper", "next": "leftWhisper" },
      { "label": "Follow the right whisper", "next": "rightWhisper" },
      { "label": "Follow the whisper behind you", "next": "backWhisper" }
    ]
  },

  "leftWhisper": {
    "text": "You walk left and immediately fall into a bean pit. Thousands of beans stare at you.",
    "choices": [
      { "label": "Stare back", "next": "beanStare" },
      { "label": "Try to swim upward", "next": "beanSwim" }
    ]
  },

  "beanStare": {
    "text": "The beans blink in unison. You feel judged.",
    "choices": [
      { "label": "Blink back", "next": "endingBlink" },
      { "label": "Assert dominance", "next": "dominanceAttempt" }
    ]
  },

  "dominanceAttempt": {
    "text": "You puff your chest. The beans puff back. You are outnumbered.",
    "choices": [
      { "label": "Retreat", "next": "endingRetreatBeans" },
      { "label": "Challenge the beans to a duel", "next": "beanDuel" }
    ]
  },

  "beanDuel": {
    "text": "A single bean rolls forward. It is the champion.",
    "choices": [
      { "label": "Fight the bean", "next": "endingBeanDefeat" },
      { "label": "Lose intentionally", "next": "endingBeanMercy" }
    ]
  },

  "beanSwim": {
    "text": "You swim through the beans like a majestic dolphin. A bean dolphin.",
    "choices": [
      { "label": "Continue swimming", "next": "beanOcean" },
      { "label": "Stop and reflect on your life choices", "next": "endingReflection" }
    ]
  },

  "beanOcean": {
    "text": "The pit expands into an ocean of beans. A pirate ship approaches.",
    "choices": [
      { "label": "Board the ship", "next": "beanPirates" },
      { "label": "Hide underwater", "next": "endingDrownBeans" }
    ]
  },

  "beanPirates": {
    "text": "The Bean Pirates welcome you aboard. Their captain is a giant bean with an eyepatch.",
    "choices": [
      { "label": "Join the crew", "next": "beanCrew" },
      { "label": "Mutiny", "next": "beanMutiny" }
    ]
  },

  "beanCrew": {
    "text": "You become a bean pirate. Your first task: steal beans from other pirates.",
    "choices": [
      { "label": "Accept", "next": "endingPirateLife" },
      { "label": "Refuse", "next": "endingWalkPlank" }
    ]
  },

  "beanMutiny": {
    "text": "You attempt a mutiny. The beans are not impressed.",
    "choices": [
      { "label": "Fight anyway", "next": "endingMutinyFail" },
      { "label": "Apologize", "next": "endingMutinyApology" }
    ]
  },

  "rightWhisper": {
    "text": "You follow the right whisper and find a glowing vending machine.",
    "choices": [
      { "label": "Buy a snack", "next": "vendingSnack" },
      { "label": "Kick the machine", "next": "endingVendingKick" },
      { "label": "Crawl inside", "next": "vendingInside" }
    ]
  },

  "vendingSnack": {
    "text": "You press a button. The machine dispenses a single bean.",
    "choices": [
      { "label": "Eat it", "next": "endingCursedBean" },
      { "label": "Save it", "next": "beanSaved" }
    ]
  },

  "beanSaved": {
    "text": "The bean glows. It whispers: 'I am the Key Bean.'",
    "choices": [
      { "label": "Ask what it unlocks", "next": "keyBeanLore" },
      { "label": "Throw it", "next": "endingThrowKeyBean" }
    ]
  },

  "keyBeanLore": {
    "text": "'I unlock the path to the True Beans... but only if you prove worthy.'",
    "choices": [
      { "label": "Prove worthiness", "next": "worthinessTest" },
      { "label": "Eat the Key Bean", "next": "endingEatKeyBean" }
    ]
  },

  "worthinessTest": {
    "text": "The Key Bean asks: 'What is the opposite of beans?'",
    "choices": [
      { "label": "No beans", "next": "endingUnworthy2" },
      { "label": "More beans", "next": "endingUnworthy3" },
      { "label": "There is no opposite. Beans simply are.", "next": "keyBeanOpens" }
    ]
  },

  "keyBeanOpens": {
    "text": "The Key Bean glows brightly. A portal opens.",
    "choices": [
      { "label": "Enter the portal", "next": "portalRealm" }
    ]
  },

  "portalRealm": {
    "text": "You enter a realm made entirely of bean energy. A cosmic figure approaches.",
    "choices": [
      { "label": "Speak to the figure", "next": "cosmicFigure" },
      { "label": "Run away", "next": "endingRunPortal" }
    ]
  },

  "cosmicFigure": {
    "text": "The figure says: 'I am the Bean Architect. I designed your suffering.'",
    "choices": [
      { "label": "Ask why", "next": "architectWhy" },
      { "label": "Punch the architect", "next": "endingPunchArchitect" }
    ]
  },

  "architectWhy": {
    "text": "'Because it is funny,' the Architect says.",
    "choices": [
      { "label": "Accept this", "next": "architectAccept" },
      { "label": "Reject this", "next": "architectReject" }
    ]
  },

  "architectAccept": {
    "text": "The Architect nods. 'Then you are ready for the True Beans.'",
    "choices": [
      { "label": "Continue", "next": "trueBeansReveal" }
    ]
  },

  "architectReject": {
    "text": "The Architect shrugs. 'Too bad.'",
    "choices": [
      { "label": "Continue anyway", "next": "trueBeansReveal" }
    ]
  },

  "vendingInside": {
    "text": "You crawl inside the vending machine. It is bigger on the inside.",
    "choices": [
      { "label": "Explore", "next": "vendingWorld" },
      { "label": "Leave", "next": "endingStuck" }
    ]
  },

  "vendingWorld": {
    "text": "You discover a tiny civilization of vending machine people.",
    "choices": [
      { "label": "Become their king", "next": "endingVendingKing" },
      { "label": "Declare war", "next": "endingVendingWar" }
    ]
  },

  "backWhisper": {
    "text": "You turn around and walk backward into a mysterious elevator.",
    "choices": [
      { "label": "Press a random button", "next": "elevatorChaos" },
      { "label": "Press ALL the buttons", "next": "endingAllButtons" }
    ]
  },

  "elevatorChaos": {
    "text": "The elevator descends for 14 hours. Music plays. You lose track of time.",
    "choices": [
      { "label": "Wait patiently", "next": "endingElevatorWait" },
      { "label": "Break the elevator", "next": "elevatorBreak" }
    ]
  },

  "elevatorBreak": {
    "text": "You break the elevator. It plummets into the Bean Underworld.",
    "choices": [
      { "label": "Explore the underworld", "next": "beanUnderworld" },
      { "label": "Cry", "next": "endingCry" }
    ]
  },

  "beanUnderworld": {
    "text": "You meet the Bean Reaper. He looks tired.",
    "choices": [
      { "label": "Ask for your beans", "next": "reaperDeal" },
      { "label": "Challenge him", "next": "endingReaperFight" }
    ]
  },

  "reaperDeal": {
    "text": "'I can return your beans... for a price.'",
    "choices": [
      { "label": "Ask the price", "next": "reaperPrice" },
      { "label": "Refuse", "next": "endingRefuseReaper" }
    ]
  },

  "reaperPrice": {
    "text": "'Bring me the Soul of a Raccoon.'",
    "choices": [
      { "label": "Accept the quest", "next": "raccoonSoulQuest" },
      { "label": "Refuse", "next": "endingRefuseReaper" }
    ]
  },

  "raccoonSoulQuest": {
    "text": "You must now hunt the raccoon who stole your beans.",
    "choices": [
      { "label": "Track the raccoon", "next": "raccoonTrack" },
      { "label": "Give up", "next": "endingGiveUp" }
    ]
  },

  "raccoonTrack": {
    "text": "You find the raccoon meditating under a waterfall.",
    "choices": [
      { "label": "Steal its soul", "next": "endingSoulSteal" },
      { "label": "Ask politely", "next": "endingRaccoonRefuses" }
    ]
  },

  "endingBlink": { "text": "ENDING: You blink. The beans blink. You die of awkwardness.", "choices": [] },
  "endingRetreatBeans": { "text": "ENDING: You retreat. The beans gossip about you.", "choices": [] },
  "endingBeanDefeat": { "text": "ENDING: The bean defeats you. Embarrassing.", "choices": [] },
  "endingBeanMercy": { "text": "ENDING: You lose intentionally. The beans respect your humility.", "choices": [] },
  "endingReflection": { "text": "ENDING: You reflect too hard and implode.", "choices": [] },
  "endingDrownBeans": { "text": "ENDING: You drown in beans. A strange way to go.", "choices": [] },
  "endingPirateLife": { "text": "ENDING: You live as a bean pirate forever.", "choices": [] },
  "endingWalkPlank": { "text": "ENDING: You walk the plank into bean-infested waters.", "choices": [] },
  "endingMutinyFail": { "text": "ENDING: The mutiny fails instantly.", "choices": [] },
  "endingMutinyApology": { "text": "ENDING: You apologize. The beans forgive you.", "choices": [] },
  "endingVendingKick": { "text": "ENDING: You kick the machine. It kicks back.", "choices": [] },
  "endingCursedBean": { "text": "ENDING: The bean curses you. You turn into a bean.", "choices": [] },
  "endingThrowKeyBean": { "text": "ENDING: You throw the Key Bean. It cries.", "choices": [] },
  "endingEatKeyBean": { "text": "ENDING: You eat the Key Bean. You explode.", "choices": [] },
  "endingRunPortal": { "text": "ENDING: You run. The portal judges you.", "choices": [] },
  "endingPunchArchitect": { "text": "ENDING: You punch the Architect. He deletes you.", "choices": [] },
  "endingStuck": { "text": "ENDING: You get stuck inside the vending machine forever.", "choices": [] },
  "endingVendingKing": { "text": "ENDING: You become king of the vending people.", "choices": [] },
  "endingVendingWar": { "text": "ENDING: You declare war. You lose instantly.", "choices": [] },
  "endingAllButtons": { "text": "ENDING: You press all the buttons. The elevator screams.", "choices": [] },
  "endingElevatorWait": { "text": "ENDING: You wait 200 years. The elevator never stops.", "choices": [] },
  "endingReaperFight": { "text": "ENDING: You fight the Bean Reaper. He wins.", "choices": [] },
  "endingRefuseReaper": { "text": "ENDING: You refuse. The Reaper shrugs and leaves.", "choices": [] },
  "endingSoulSteal": { "text": "ENDING: You steal the raccoon's soul. You monster.", "choices": [] },
  "endingRaccoonRefuses": { "text": "ENDING: The raccoon refuses. You respect its boundaries.", "choices": [] }
  ,
  "forestMeditation": {
    "text": "You sit on a mossy rock and meditate. The forest hums. Something ancient stirs.",
    "choices": [
      { "label": "Listen closely", "next": "longJourneyStart" },
      { "label": "Ignore it", "next": "endingIgnoreForest" }
    ]
  },

  "endingIgnoreForest": {
    "text": "ENDING: You ignore the ancient forest whisper. It ignores you back. Mutual disappointment.",
    "choices": []
  },

  "bureauBasement": {
    "text": "A detective whispers: 'If you really want answers… check the basement.'",
    "choices": [
      { "label": "Go to the basement", "next": "basementDoor" },
      { "label": "Refuse", "next": "endingCoward" }
    ]
  },

  "basementDoor": {
    "text": "The basement door is covered in warning signs. One reads: 'BEAN PROPHECY STORAGE.'",
    "choices": [
      { "label": "Enter", "next": "prophecyRoom" },
      { "label": "Knock politely", "next": "endingBasementKnock" }
    ]
  },

  "endingBasementKnock": {
    "text": "ENDING: You knock. Something knocks back. You flee instantly.",
    "choices": []
  },

  "prophecyRoom": {
    "text": "Scrolls float in the air. A glowing one drifts toward you.",
    "choices": [
      { "label": "Read the scroll", "next": "prophecyRead" },
      { "label": "Eat the scroll", "next": "endingEatScroll" }
    ]
  },

  "endingEatScroll": {
    "text": "ENDING: You eat the prophecy scroll. It tastes like destiny and paper.",
    "choices": []
  },

  "prophecyRead": {
    "text": "The scroll reads: 'THE ONE WHO SEEKS THE TRUE BEANS MUST WALK THE LONG ROAD.'",
    "choices": [
      { "label": "Accept the prophecy", "next": "longJourneyStart" },
      { "label": "Reject destiny", "next": "endingRejectDestiny" }
    ]
  },

  "endingRejectDestiny": {
    "text": "ENDING: You reject destiny. Destiny shrugs and leaves.",
    "choices": []
  },

  "raccoonMeditation": {
    "text": "The raccoon bandit pauses mid‑fight. 'Wait… do you hear that?'",
    "choices": [
      { "label": "Listen", "next": "longJourneySidePath" },
      { "label": "Say no", "next": "endingNoListen" }
    ]
  },

  "endingNoListen": {
    "text": "ENDING: You say no. The raccoon is offended and leaves.",
    "choices": []
  },

  "breakRealityDeep": {
    "text": "The crack in reality widens. You glimpse a distant road stretching into infinity.",
    "choices": [
      { "label": "Step toward the road", "next": "longJourneyStart" },
      { "label": "Close the crack", "next": "start" }
    ]
  },

  "forestStoolInspect": {
    "text": "You inspect the weird stool thingy. It vibrates softly.",
    "choices": [
      { "label": "Sit on it", "next": "stoolSit" },
      { "label": "Kick it", "next": "endingStoolKick" }
    ]
  },

  "endingStoolKick": {
    "text": "ENDING: You kick the stool. It screams. You run.",
    "choices": []
  },

  "stoolSit": {
    "text": "You sit. The stool sinks into the ground, taking you with it.",
    "choices": [
      { "label": "Let it take you", "next": "longJourneySidePath" },
      { "label": "Try to escape", "next": "endingStoolTrap" }
    ]
  },

  "endingStoolTrap": {
    "text": "ENDING: You try to escape. The stool holds you tighter. You live there now.",
    "choices": []
  },

  "neighborWeirdAttic": {
    "text": "Your neighbor whispers: 'If you really want answers… check my attic.'",
    "choices": [
      { "label": "Go to the attic", "next": "atticStart" },
      { "label": "Refuse", "next": "endingCoward" }
    ]
  },

  "atticStart": {
    "text": "The attic is filled with bean‑shaped relics. One glows faintly.",
    "choices": [
      { "label": "Touch the relic", "next": "atticRelic" },
      { "label": "Back away", "next": "start" }
    ]
  },

  "atticRelic": {
    "text": "The relic pulses. A voice whispers: 'Walk the long path…'",
    "choices": [
      { "label": "Follow the voice", "next": "longJourneyStart" },
      { "label": "Ignore it", "next": "endingIgnoreRelic" }
    ]
  },

  "endingIgnoreRelic": {
    "text": "ENDING: You ignore the relic. It explodes out of spite.",
    "choices": []
  },

  "bureauSecretHallway": {
    "text": "A hidden hallway opens behind a filing cabinet. A sign reads: 'BEAN QUEST INITIATION.'",
    "choices": [
      { "label": "Enter the hallway", "next": "hallwayEnter" },
      { "label": "Close the cabinet", "next": "start" }
    ]
  },

  "hallwayEnter": {
    "text": "The hallway stretches impossibly far. You hear chanting.",
    "choices": [
      { "label": "Walk toward the chanting", "next": "longJourneySidePath" },
      { "label": "Run away", "next": "endingCoward" }
    ]
  },

  "forestDeepHole": {
    "text": "You find a deep hole in the forest. A sign reads: 'BEAN TRIALS BELOW.'",
    "choices": [
      { "label": "Jump in", "next": "longJourneyStart" },
      { "label": "Throw a rock in", "next": "endingRockThrow" }
    ]
  },

  "endingRockThrow": {
    "text": "ENDING: You throw a rock. Something throws it back harder.",
    "choices": []
  },

  "cosmicBeanEcho": {
    "text": "A faint echo of the cosmic bean calls to you from beyond reality.",
    "choices": [
      { "label": "Answer the call", "next": "longJourneySidePath" },
      { "label": "Hang up", "next": "endingHangUp" }
    ]
  },

  "endingHangUp": {
    "text": "ENDING: You hang up on a cosmic bean. It blocks your number.",
    "choices": []
  }
  ,
  "beanCultEncounter": {
    "text": "A hooded figure approaches you in the forest. 'Do you seek… the Bean Truth?'",
    "choices": [
      { "label": "Yes", "next": "beanCultChamber" },
      { "label": "No", "next": "endingCultRefusal" },
      { "label": "Ask if they have snacks", "next": "endingCultSnacks" }
    ]
  },

  "beanCultChamber": {
    "text": "You are led into a hidden underground chamber. Dozens of robed figures chant 'BEAN! BEAN! BEAN!'",
    "choices": [
      { "label": "Join the chant", "next": "cultChant" },
      { "label": "Ask about the prophecy", "next": "cultProphecy" }
    ]
  },

  "cultChant": {
    "text": "You chant with them. The room vibrates. A glowing bean descends from the ceiling.",
    "choices": [
      { "label": "Touch the glowing bean", "next": "longJourneyStart" },
      { "label": "Bow to it", "next": "endingCultBow" }
    ]
  },

  "cultProphecy": {
    "text": "The cult leader whispers: 'Only the Long Journey reveals the True Beans.'",
    "choices": [
      { "label": "Accept the path", "next": "longJourneyStart" },
      { "label": "Reject the cult", "next": "endingCultReject" }
    ]
  },

  "endingCultRefusal": {
    "text": "ENDING: You refuse the cult. They hiss and vanish into the bushes.",
    "choices": []
  },

  "endingCultSnacks": {
    "text": "ENDING: They offer you a stale granola bar. You regret asking.",
    "choices": []
  },

  "endingCultBow": {
    "text": "ENDING: You bow. The glowing bean falls on your head.",
    "choices": []
  },

  "endingCultReject": {
    "text": "ENDING: You reject the cult. They curse your future bean harvest.",
    "choices": []
  },

  "beanCasinoEntrance": {
    "text": "You stumble upon a neon sign: 'BEAN CASINO — ALL OR NOTHING.'",
    "choices": [
      { "label": "Enter", "next": "beanCasino" },
      { "label": "Walk away", "next": "start" }
    ]
  },

  "beanCasino": {
    "text": "Inside, raccoons in tuxedos run slot machines. A dealer bean waves you over.",
    "choices": [
      { "label": "Play blackjack", "next": "casinoBlackjack" },
      { "label": "Play bean slots", "next": "casinoSlots" },
      { "label": "Ask about the VIP room", "next": "casinoVIP" }
    ]
  },

  "casinoBlackjack": {
    "text": "You sit at a table. The dealer bean deals you two cards: 7 and BEAN.",
    "choices": [
      { "label": "Hit", "next": "endingBlackjackBust" },
      { "label": "Stand", "next": "endingBlackjackWin" }
    ]
  },

  "endingBlackjackBust": {
    "text": "ENDING: You bust. The dealer bean laughs at you.",
    "choices": []
  },

  "endingBlackjackWin": {
    "text": "ENDING: You win! Your prize is a coupon for 10% off beans.",
    "choices": []
  },

  "casinoSlots": {
    "text": "You pull the lever. The slots spin: BEAN — BEAN — ???",
    "choices": [
      { "label": "Wait", "next": "endingSlotsLose" },
      { "label": "Kick the machine", "next": "endingSlotsKick" }
    ]
  },

  "endingSlotsLose": {
    "text": "ENDING: The third slot is a raccoon. You lose everything.",
    "choices": []
  },

  "endingSlotsKick": {
    "text": "ENDING: You kick the machine. It explodes into beans.",
    "choices": []
  },

  "casinoVIP": {
    "text": "The VIP room is guarded by a bean bouncer. He scans you.",
    "choices": [
      { "label": "Bribe him", "next": "endingVIPBribe" },
      { "label": "Tell him you seek the Long Journey", "next": "longJourneySidePath" }
    ]
  },

  "endingVIPBribe": {
    "text": "ENDING: You bribe him with a granola bar. He eats it and denies you anyway.",
    "choices": []
  },

  "beanCourtroom": {
    "text": "You are summoned to Bean Court. A judge bean bangs a tiny gavel.",
    "choices": [
      { "label": "Plead guilty", "next": "endingCourtGuilty" },
      { "label": "Plead innocent", "next": "courtInnocent" }
    ]
  },

  "endingCourtGuilty": {
    "text": "ENDING: You plead guilty. You are sentenced to 30 years of bean sorting.",
    "choices": []
  },

  "courtInnocent": {
    "text": "The judge bean narrows its eyes. 'Prove it.'",
    "choices": [
      { "label": "Present evidence", "next": "courtEvidence" },
      { "label": "Run", "next": "endingCourtRun" }
    ]
  },

  "courtEvidence": {
    "text": "You present a single bean shell as evidence.",
    "choices": [
      { "label": "Claim it is sacred", "next": "longJourneyStart" },
      { "label": "Claim it is cursed", "next": "endingCourtCursed" }
    ]
  },

  "endingCourtRun": {
    "text": "ENDING: You run. The bean bailiffs chase you.",
    "choices": []
  },

  "endingCourtCursed": {
    "text": "ENDING: The courtroom panics. Everyone flees.",
    "choices": []
  },

  "beanTrainStation": {
    "text": "A train station appears where it definitely wasn’t before. A sign reads: 'BEAN EXPRESS — DESTINY LINE.'",
    "choices": [
      { "label": "Board the train", "next": "beanTrain" },
      { "label": "Walk away", "next": "start" }
    ]
  },

  "beanTrain": {
    "text": "You board the train. The conductor bean tips its hat.",
    "choices": [
      { "label": "Ask where the train goes", "next": "trainDestination" },
      { "label": "Sit quietly", "next": "endingTrainQuiet" }
    ]
  },

  "trainDestination": {
    "text": "'This train only goes one place,' the conductor says. 'The Long Journey.'",
    "choices": [
      { "label": "Accept your fate", "next": "longJourneyStart" },
      { "label": "Jump off the train", "next": "endingTrainJump" }
    ]
  },

  "endingTrainQuiet": {
    "text": "ENDING: You sit quietly. The train never stops.",
    "choices": []
  },

  "endingTrainJump": {
    "text": "ENDING: You jump off and land in a bush. A raccoon laughs at you.",
    "choices": []
  },

  "beanPopeEncounter": {
    "text": "A holy bean wearing a tall hat approaches. 'My child… your journey is long.'",
    "choices": [
      { "label": "Ask for a blessing", "next": "popeBlessing" },
      { "label": "Ask for beans", "next": "endingPopeGreedy" }
    ]
  },

  "popeBlessing": {
    "text": "The Bean Pope blesses you. You feel warm and slightly seasoned.",
    "choices": [
      { "label": "Accept the holy path", "next": "longJourneySidePath" },
      { "label": "Reject the blessing", "next": "endingPopeReject" }
    ]
  },

  "endingPopeGreedy": {
    "text": "ENDING: You ask for beans. The Bean Pope sighs and walks away.",
    "choices": []
  },

  "endingPopeReject": {
    "text": "ENDING: You reject the blessing. Lightning strikes a nearby tree.",
    "choices": []
  }

}

